szndaogen/VERSION
szndaogen/__init__.py
szndaogen/cli.py
szndaogen/cli_wizard.py
szndaogen/config.py
szndaogen/data_access/__init__.py
szndaogen/data_access/db.py
szndaogen/data_access/manager_base.py
szndaogen/data_access/model_base.py
szndaogen/data_access/test_model_base.py
szndaogen/generator/__init__.py
szndaogen/generator/analyser.py
szndaogen/generator/datatypes.py
szndaogen/templates/manager.jinja
szndaogen/templates/manager_base.jinja
szndaogen/templates/model.jinja
szndaogen/tools/__init__.py
szndaogen/tools/auto_group.py
szndaogen/tools/cli_colors.py
szndaogen/tools/log.py
szndaogen/tools/setuptools.py
szndaogen/tools/test_auto_group.py
szndaogen-2.4.6.dist-info/LICENSE
szndaogen-2.4.6.dist-info/METADATA
szndaogen-2.4.6.dist-info/WHEEL
szndaogen-2.4.6.dist-info/entry_points.txt
szndaogen-2.4.6.dist-info/top_level.txt
szndaogen-2.4.6.dist-info/RECORD
