Metadata-Version: 2.1
Name: szndaogen
Version: 2.4.6
Summary: SZN Database Access Object Generator for MySQL. Generates Models and DataManagers from existing MySQL database structure.
Home-page: https://github.com/seznam/szndaogen
Author: Ales Adamek, Filip Cima, Richard Paprok
Author-email: hpo.sport@firma.seznam.cz
License: UNKNOWN
Platform: UNKNOWN
Classifier: Programming Language :: Python :: 3
Classifier: License :: OSI Approved :: MIT License
Classifier: Operating System :: OS Independent
Requires-Python: >=3.6
Requires-Dist: jinja2
Requires-Dist: mysql-connector-python (==8.0.29)
Requires-Dist: pytest
Requires-Dist: sqlparse
